kplanes/__init__.py
kplanes/kplanes.py
kplanes/kplanes_configs.py
kplanes/kplanes_field.py
kplanes_nerfstudio-0.5.2.dist-info/LICENSE.txt
kplanes_nerfstudio-0.5.2.dist-info/METADATA
kplanes_nerfstudio-0.5.2.dist-info/WHEEL
kplanes_nerfstudio-0.5.2.dist-info/entry_points.txt
kplanes_nerfstudio-0.5.2.dist-info/top_level.txt
kplanes_nerfstudio-0.5.2.dist-info/RECORD
