Metadata-Version: 2.1
Name: kplanes-nerfstudio
Version: 0.5.2
Summary: K-Planes nerfstudio integration
Author: Sara Fridovich-Keil
Author-email: Giacomo Meanti <giacomo.meanti@iit.it>
License: BSD 3-Clause
License-File: LICENSE.txt
Requires-Dist: nerfstudio (>=0.2.0)
